__init__.py
_ver.py
xExample1/t.py
xExample2/t.py
hg_xExample-0.3.dist-info/METADATA
hg_xExample-0.3.dist-info/WHEEL
hg_xExample-0.3.dist-info/top_level.txt
hg_xExample-0.3.dist-info/RECORD
